numwords/__init__.py
numwords/core.py
numwords/mappings.py
numwords-2.0.0.dist-info/LICENSE
numwords-2.0.0.dist-info/METADATA
numwords-2.0.0.dist-info/WHEEL
numwords-2.0.0.dist-info/top_level.txt
numwords-2.0.0.dist-info/RECORD
