Metadata-Version: 2.1
Name: numwords
Version: 2.0.0
Home-page: https://github.com/TheAnkurGoswami/NumWords
Author: Ankur Goswami
Author-email: ankurgoswami1401@gmail.com
License: MIT License
Classifier: Programming Language :: Python :: 3
Classifier: License :: OSI Approved :: MIT License
Classifier: Operating System :: OS Independent
Requires-Python: >=3.8
License-File: LICENSE
Requires-Dist: typing
